minipam/__init__.py
minipam/__main__.py
minipam/ipam.py
minipam/utils.py
minipam/version.py
tests/__init__.py
tests/test_ipam.py
tests/test_main.py
tests/test_utils.py
minipam-0.0.1.dev3.dist-info/LICENSE
minipam-0.0.1.dev3.dist-info/METADATA
minipam-0.0.1.dev3.dist-info/WHEEL
minipam-0.0.1.dev3.dist-info/entry_points.txt
minipam-0.0.1.dev3.dist-info/top_level.txt
minipam-0.0.1.dev3.dist-info/RECORD
